django_ftl/__init__.py
django_ftl/apps.py
django_ftl/autoreload.py
django_ftl/bundles.py
django_ftl/conf.py
django_ftl/middleware.py
django_ftl/models.py
django_ftl/utils.py
django_ftl/templatetags/__init__.py
django_ftl/templatetags/ftl.py
django_ftl-0.14.dist-info/AUTHORS.rst
django_ftl-0.14.dist-info/LICENSE
django_ftl-0.14.dist-info/METADATA
django_ftl-0.14.dist-info/WHEEL
django_ftl-0.14.dist-info/top_level.txt
django_ftl-0.14.dist-info/RECORD
